dummio/__init__.py
dummio/constants.py
dummio/dill.py
dummio/json.py
dummio/onnx.py
dummio/orjson.py
dummio/pickle.py
dummio/protocol.py
dummio/pydantic.py
dummio/text.py
dummio/yaml.py
dummio/mashumaro/json.py
dummio/mashumaro/yaml.py
dummio/numpy/__init__.py
dummio/numpy/ndarray_io.py
dummio/pandas/__init__.py
dummio/pandas/df_csv.py
dummio/pandas/df_feather.py
dummio/pandas/df_io.py
dummio/pandas/df_parquet.py
dummio/pandas/series_parquet.py
dummio/pandas/utils.py
dummio-1.10.2.dist-info/METADATA
dummio-1.10.2.dist-info/WHEEL
dummio-1.10.2.dist-info/licenses/LICENSE
dummio-1.10.2.dist-info/RECORD
