Metadata-Version: 2.4
Name: dummio
Version: 1.10.2
Summary: Easiest-possible IO for basic file types.
Project-URL: Source, https://github.com/zkurtz/dummio
Author-email: Zach Kurtz <zkurtz@gmail.com>
License-File: LICENSE
Requires-Python: >=3.10
Requires-Dist: universal-pathlib>=0.3.2
